funkcium
