Metadata-Version: 2.1
Name: funkcium
Version: 0.1.6
Summary: Yet Another Python functional library, with scala inspiration
Home-page: https://github.com/nykh/funkcium
Author: nykh
Author-email: nykh.pypi.199421@tryninja.io
License: MIT
Platform: UNKNOWN
Classifier: Programming Language :: Python
Classifier: Programming Language :: Python :: 3
Classifier: Development Status :: 3 - Alpha
Classifier: Intended Audience :: Developers
Classifier: License :: OSI Approved :: BSD License
Classifier: Operating System :: OS Independent
Classifier: Topic :: Software Development
Classifier: Topic :: Software Development :: Libraries :: Python Modules
